README.md
setup.py
br_nome_gen/__init__.py
br_nome_gen/br_nome_gen.py
br_nome_gen.egg-info/PKG-INFO
br_nome_gen.egg-info/SOURCES.txt
br_nome_gen.egg-info/dependency_links.txt
br_nome_gen.egg-info/top_level.txt