Metadata-Version: 2.1
Name: br-nome-gen
Version: 1.0.0
Summary: A generator of Brazilian typical names.
Home-page: https://github.com/victorwss/br-nome-gen
Author: Victor Williams Stafusa da Silva
Author-email: victorwssilva@gmail.com
License: UNKNOWN
Platform: UNKNOWN
Classifier: Programming Language :: Python :: 3
Classifier: License :: OSI Approved :: MIT License
Classifier: Operating System :: OS Independent
